uncle_ben/__init__.py
uncle_ben/basemodel.py
uncle_ben/command.py
uncle_ben/logging.py
uncle_ben/repository.py
uncle_ben/results.py
uncle_ben/analysers/__init__.py
uncle_ben/analysers/base.py
uncle_ben/analysers/git.py
uncle_ben/analysers/package_usage.py
uncle_ben/analysers/pylama.py
uncle_ben/analysers/ci/__init__.py
uncle_ben/analysers/ci/bitbucket.py
uncle_ben/analysers/ci/gitlab.py
uncle_ben/analysers/radon/__init__.py
uncle_ben/analysers/radon/common.py
uncle_ben/analysers/radon/halstead.py
uncle_ben/analysers/radon/maintainability.py
uncle_ben/analysers/radon/mccabe.py
uncle_ben/analysers/radon/rank.py
uncle_ben/analysers/radon/raw.py
uncle_ben-0.2.data/scripts/uncle-ben.py
uncle_ben-0.2.dist-info/METADATA
uncle_ben-0.2.dist-info/WHEEL
uncle_ben-0.2.dist-info/top_level.txt
uncle_ben-0.2.dist-info/RECORD
